README.md
setup.py
nasa/__init__.py
nasa/apod.py
nasa_api.egg-info/PKG-INFO
nasa_api.egg-info/SOURCES.txt
nasa_api.egg-info/dependency_links.txt
nasa_api.egg-info/top_level.txt