Metadata-Version: 2.1
Name: nasa-api
Version: 0.0.1
Summary: An API Wrapper for the Nasa API
Home-page: UNKNOWN
Author: Bruce
Author-email: brucealt69@gmail.com
License: UNKNOWN
Platform: UNKNOWN
Classifier: Programming Language :: Python :: 3
Classifier: License :: OSI Approved :: MIT License
Classifier: Operating System :: OS Independent
Requires-Python: >=3.6
